[
  {"id": "nordic-pantry", "name": "Nordic Pantry", "file": "theme-nordic-pantry.css", "preview_color": "#7A5C42", "sort_order": 1, "suggested": true},
  {"id": "chalkboard-bistro", "name": "Chalkboard Bistro", "file": "theme-chalkboard-bistro.css", "preview_color": "#E8C547", "sort_order": 2, "suggested": true},
  {"id": "warm-terracotta", "name": "Terracotta & Sage", "file": "theme-warm-terracotta.css", "preview_color": "#C4622D", "sort_order": 3, "suggested": true},
  {"id": "warm-modern", "name": "Warm & Modern", "file": "theme-warm-modern.css", "preview_color": "#C8873A", "sort_order": 4, "suggested": true},
  {"id": "apple-fitness", "name": "Apple Fitness", "file": "theme-apple-fitness.css", "preview_color": "#30D158", "sort_order": 5, "suggested": false},
  {"id": "brutalist", "name": "Brutalist", "file": "theme-brutalist.css", "preview_color": "#000000", "sort_order": 6, "suggested": false},
  {"id": "coastal-kitchen", "name": "Coastal Kitchen", "file": "theme-coastal-kitchen.css", "preview_color": "#2E7DB5", "sort_order": 7, "suggested": false},
  {"id": "forest-forager", "name": "Forest Forager", "file": "theme-forest-forager.css", "preview_color": "#4A5E2F", "sort_order": 8, "suggested": false},
  {"id": "pop-art-diner", "name": "Pop Art Diner", "file": "theme-pop-art-diner.css", "preview_color": "#D32F2F", "sort_order": 9, "suggested": false}
]
